LICENSE.md
README.md
setup.cfg
setup.py
src/py_wrike_v4/__init__.py
src/py_wrike_v4/helpers.py
src/py_wrike_v4/wrike.py
src/py_wrike_v4.egg-info/PKG-INFO
src/py_wrike_v4.egg-info/SOURCES.txt
src/py_wrike_v4.egg-info/dependency_links.txt
src/py_wrike_v4.egg-info/requires.txt
src/py_wrike_v4.egg-info/top_level.txt