Metadata-Version: 2.1
Name: py-wrike-v4
Version: 0.15
Summary: UNKNOWN
Home-page: https://github.com/Raziel619/py_wrike_v4
Author: Govinda Hosein
Author-email: raziel619dev@gmail.com
License: MIT
Keywords: wrike
Platform: UNKNOWN
